[
  {
    "text": "data", 
    "size": 322.3970660996
  }, 
  {
    "text": "similar", 
    "size": 195.0930708956
  }, 
  {
    "text": "r", 
    "size": 180.2990258671
  }, 
  {
    "text": "model", 
    "size": 139.1498671659
  }, 
  {
    "text": "matrix", 
    "size": 115.0265776787
  }, 
  {
    "text": "would", 
    "size": 109.6185681474
  }, 
  {
    "text": "like", 
    "size": 107.7408396409
  }, 
  {
    "text": "one", 
    "size": 96.1197112937
  }, 
  {
    "text": "recommend", 
    "size": 92.028558482
  }, 
  {
    "text": "learn", 
    "size": 88.3909388859
  }, 
  {
    "text": "number", 
    "size": 78.3515753507
  }, 
  {
    "text": "problem", 
    "size": 76.730300187
  }, 
  {
    "text": "time", 
    "size": 76.0092849421
  }, 
  {
    "text": "algorithm", 
    "size": 71.9275291242
  }, 
  {
    "text": "also", 
    "size": 71.6190772578
  }, 
  {
    "text": "instanc", 
    "size": 70.1400117738
  }, 
  {
    "text": "distribut", 
    "size": 68.9152138003
  }, 
  {
    "text": "work", 
    "size": 66.8452079402
  }, 
  {
    "text": "set", 
    "size": 64.9412011261
  }
]